prompt_toolkit2/__init__.py
prompt_toolkit2/auto_suggest.py
prompt_toolkit2/buffer.py
prompt_toolkit2/cache.py
prompt_toolkit2/document.py
prompt_toolkit2/enums.py
prompt_toolkit2/history.py
prompt_toolkit2/keys.py
prompt_toolkit2/log.py
prompt_toolkit2/mouse_events.py
prompt_toolkit2/patch_stdout.py
prompt_toolkit2/renderer.py
prompt_toolkit2/search.py
prompt_toolkit2/selection.py
prompt_toolkit2/token.py
prompt_toolkit2/utils.py
prompt_toolkit2/validation.py
prompt_toolkit2/win32_types.py
prompt_toolkit2/application/__init__.py
prompt_toolkit2/application/application.py
prompt_toolkit2/application/current.py
prompt_toolkit2/application/dummy.py
prompt_toolkit2/application/run_in_terminal.py
prompt_toolkit2/clipboard/__init__.py
prompt_toolkit2/clipboard/base.py
prompt_toolkit2/clipboard/in_memory.py
prompt_toolkit2/clipboard/pyperclip.py
prompt_toolkit2/completion/__init__.py
prompt_toolkit2/completion/base.py
prompt_toolkit2/completion/filesystem.py
prompt_toolkit2/completion/fuzzy_completer.py
prompt_toolkit2/completion/word_completer.py
prompt_toolkit2/contrib/__init__.py
prompt_toolkit2/contrib/completers/__init__.py
prompt_toolkit2/contrib/completers/system.py
prompt_toolkit2/contrib/regular_languages/__init__.py
prompt_toolkit2/contrib/regular_languages/compiler.py
prompt_toolkit2/contrib/regular_languages/completion.py
prompt_toolkit2/contrib/regular_languages/lexer.py
prompt_toolkit2/contrib/regular_languages/regex_parser.py
prompt_toolkit2/contrib/regular_languages/validation.py
prompt_toolkit2/contrib/telnet/__init__.py
prompt_toolkit2/contrib/telnet/log.py
prompt_toolkit2/contrib/telnet/protocol.py
prompt_toolkit2/contrib/telnet/server.py
prompt_toolkit2/eventloop/__init__.py
prompt_toolkit2/eventloop/async_generator.py
prompt_toolkit2/eventloop/asyncio_posix.py
prompt_toolkit2/eventloop/asyncio_win32.py
prompt_toolkit2/eventloop/base.py
prompt_toolkit2/eventloop/context.py
prompt_toolkit2/eventloop/coroutine.py
prompt_toolkit2/eventloop/defaults.py
prompt_toolkit2-2.0.11.dist-info/AUTHORS.rst
prompt_toolkit2-2.0.11.dist-info/LICENSE
prompt_toolkit2-2.0.11.dist-info/METADATA
prompt_toolkit2-2.0.11.dist-info/WHEEL
prompt_toolkit2-2.0.11.dist-info/top_level.txt
prompt_toolkit2-2.0.11.dist-info/RECORD
