Metadata-Version: 2.1
Name: prompt-toolkit2
Version: 2.0.11
Summary: Renamed fork of v2.0 prompt-toolkit
Home-page: https://github.com/jonathanslenders/python-prompt-toolkit
Author: Jonathan Slenders
License: BSD-3-Clause
Platform: UNKNOWN
Classifier: Development Status :: 5 - Production/Stable
Classifier: Intended Audience :: Developers
Classifier: License :: OSI Approved :: BSD License
Classifier: Operating System :: OS Independent
Classifier: Programming Language :: Python :: 2
Classifier: Programming Language :: Python :: 2.6
Classifier: Programming Language :: Python :: 2.7
Classifier: Programming Language :: Python :: 3
Classifier: Programming Language :: Python :: 3.3
Classifier: Programming Language :: Python :: 3.4
Classifier: Programming Language :: Python :: 3.5
Classifier: Programming Language :: Python :: 3.6
Classifier: Programming Language :: Python :: 3.7
Classifier: Programming Language :: Python
Classifier: Topic :: Software Development
Requires-Python: >=2.6, !=3.0.*, !=3.1.*, !=3.2.*
License-File: LICENSE
License-File: AUTHORS.rst
Requires-Dist: six (>=1.9.0)
Requires-Dist: wcwidth
